[
    {
        "nome": "Ana",
        "sobrenome": "Lucia",
        "empresa": "EBAC",
        "endereco": "Av. Paulista",
        "numero": "2000",
        "pais": "Brasil",
        "cidade": "São Paulo",
        "estado": "São Paulo",
        "cep": "21300200",
        "telefone": "2198527413",
        "email": "teste@teste.com"
    },
    {
        "nome": "Eduardo",
        "sobrenome": "Souza",
        "empresa": "EBAC",
        "endereco": "Av. Paulista",
        "numero": "2000",
        "pais": "Brasil",
        "cidade": "São Paulo",
        "estado": "São Paulo",
        "cep": "21300200",
        "telefone": "2198527413",
        "email": "teste@teste.com"
    },
    {
        "nome": "Morvan",
        "sobrenome": "Ferreira",
        "empresa": "EBAC",
        "endereco": "Av. Paulista",
        "numero": "2022",
        "pais": "Brasil",
        "cidade": "São Paulo",
        "estado": "São Paulo",
        "cep": "21300200",
        "telefone": "2198527413",
        "email": "teste@teste.com"
    }
]